Metadata-Version: 1.0
Name: BandG-distributions
Version: 0.1
Summary: Gaussian distributions
Home-page: UNKNOWN
Author: Cristhian Garcia
Author-email: cristhiancjgs20@gmail.com
License: UNKNOWN
Platform: UNKNOWN
